[
  {
    "id": "Command()",
    "longname": "Command",
    "name": "Command",
    "kind": "constructor",
    "memberof": "Command",
    "params": [
      {
        "type": {
          "names": [
            "string"
          ]
        },
        "description": "The ID of the command",
        "name": "ID"
      },
      {
        "type": {
          "names": [
            "MessageGenerator"
          ]
        },
        "name": "function|string|falsy"
      },
      {
        "type": {
          "names": [
            "ParentObject"
          ]
        },
        "description": "This can be a guild, plugin. This should be a command if you are registering a SubCommand.",
        "name": "parent"
      },
      {
        "type": {
          "names": [
            "CommandOptions"
          ]
        },
        "name": "options"
      }
    ],
    "order": 4
  },
  {
    "id": "CommandRegistry",
    "longname": "CommandRegistry",
    "name": "CommandRegistry",
    "scope": "global",
    "kind": "class",
    "description": "This is the CommandRegistry holds all of the commands in the world",
    "meta": {
      "lineno": 10,
      "filename": "CommandRegistry.js",
      "path": "/usr/share/Workspace/Beta/R3alB0t/lib/registry"
    },
    "order": 0
  },
  {
    "id": "chatHandler",
    "longname": "chatHandler",
    "name": "chatHandler",
    "scope": "global",
    "kind": "class",
    "description": "This is the chat handling class file. This is the command running code. Very finiky",
    "meta": {
      "lineno": 7,
      "filename": "CommandHandler.js",
      "path": "/usr/share/Workspace/Beta/R3alB0t/lib/registry/models"
    },
    "order": 1
  },
  {
    "id": "Command",
    "longname": "Command",
    "name": "Command",
    "scope": "global",
    "kind": "class",
    "description": "The Command Object",
    "meta": {
      "lineno": 19,
      "filename": "command.js",
      "path": "/usr/share/Workspace/Beta/R3alB0t/lib/registry/models"
    },
    "order": 3
  },
  {
    "id": "CommandOptions",
    "longname": "CommandOptions",
    "name": "CommandOptions",
    "scope": "global",
    "kind": "typedef",
    "description": "Options to be passed to used in a command",
    "type": {
      "names": [
        "Object"
      ]
    },
    "properties": [
      {
        "type": {
          "names": [
            "boolean"
          ]
        },
        "optional": true,
        "defaultvalue": true,
        "description": "Whether or not the command should be case sensitive",
        "name": "caseSensitive"
      },
      {
        "type": {
          "names": [
            "boolean"
          ]
        },
        "optional": true,
        "defaultvalue": false,
        "description": "Whether or not the command can only be ran in direct messages only",
        "name": "dmOnly"
      },
      {
        "type": {
          "names": [
            "boolean"
          ]
        },
        "optional": true,
        "defaultvalue": false,
        "description": "Whether or not the command can only be ran in a guild text channel. Cannot be true if dmOnly is true",
        "name": "guildOnly"
      },
      {
        "type": {
          "names": [
            "string"
          ]
        },
        "optional": true,
        "defaultvalue": "\"Default Description\"",
        "description": "The description of the command",
        "name": "description"
      }
    ],
    "meta": {
      "lineno": 4,
      "filename": "command.js",
      "path": "/usr/share/Workspace/Beta/R3alB0t/lib/registry/models"
    },
    "order": 2
  }
]
